README
cache.py
comicvine_api.py
comicvine_exceptions.py
comicvine_ui.py
setup.py
comicvine_api.egg-info/PKG-INFO
comicvine_api.egg-info/SOURCES.txt
comicvine_api.egg-info/dependency_links.txt
comicvine_api.egg-info/top_level.txt