Metadata-Version: 1.0
Name: comicvine-api
Version: 1.03
Summary: Interface to the comicvine.com API
Home-page: http://github.com/swc/comicvine_api
Author: swc/Steve
Author-email: iam@attractive.com
License: GPLv2
Platform: UNKNOWN
Classifier: Intended Audience :: Developers
Classifier: License :: OSI Approved :: GNU General Public License (GPL)
Classifier: Natural Language :: English
Classifier: Operating System :: OS Independent
Classifier: Programming Language :: Python
Classifier: Topic :: Multimedia
Classifier: Topic :: Utilities
Classifier: Topic :: Software Development :: Libraries :: Python Modules
